diff_parser/__init__.py
diff_parser-1.0.dist-info/LICENSE
diff_parser-1.0.dist-info/METADATA
diff_parser-1.0.dist-info/WHEEL
diff_parser-1.0.dist-info/top_level.txt
diff_parser-1.0.dist-info/RECORD
