Metadata-Version: 2.1
Name: diff-parser
Version: 1.0
Summary: Parse a `git diff` data or `.diff` file. Access a list of properties including filenames, filepath, source-hash, target-hash and more for every file changed.
Author-email: Shaik Abdus Samad <shaiksamad.dev@gmail.com>
License: MIT License
Project-URL: Homepage, https://github.com/shaiksamad/diff-parser.git
Project-URL: Repository, https://github.com/shaiksamad/diff-parser.git
Project-URL: Issues, https://github.com/shaiksamad/diff-parser/issues
Keywords: diff,file differences,diff parser,diffparser,diff file,git diff
Classifier: Intended Audience :: Developers
Classifier: Topic :: Software Development :: Build Tools
Classifier: License :: OSI Approved :: MIT License
Classifier: Programming Language :: Python :: 3
Classifier: Programming Language :: Python :: 3.6
Classifier: Programming Language :: Python :: 3.7
Classifier: Programming Language :: Python :: 3.8
Classifier: Programming Language :: Python :: 3.9
Requires-Python: >=3.6
License-File: LICENSE
